main.py
setup.py
dunkin_bot.egg-info/PKG-INFO
dunkin_bot.egg-info/SOURCES.txt
dunkin_bot.egg-info/dependency_links.txt
dunkin_bot.egg-info/entry_points.txt
dunkin_bot.egg-info/requires.txt
dunkin_bot.egg-info/top_level.txt